Dockerfile
MANIFEST.in
PyPI-README.md
README.md
entrypoint.py
setup.cfg
setup.py
pycg_producer/__init__.py
pycg_producer/a.py
pycg_producer/producer.py
pycg_producer.egg-info/PKG-INFO
pycg_producer.egg-info/SOURCES.txt
pycg_producer.egg-info/dependency_links.txt
pycg_producer.egg-info/requires.txt
pycg_producer.egg-info/top_level.txt